AUTHORS.rst
CONTRIBUTING.rst
HISTORY.rst
LICENSE
MANIFEST.in
README.rst
setup.cfg
setup.py
django_objectdumpdata/__init__.py
django_objectdumpdata.egg-info/PKG-INFO
django_objectdumpdata.egg-info/SOURCES.txt
django_objectdumpdata.egg-info/dependency_links.txt
django_objectdumpdata.egg-info/not-zip-safe
django_objectdumpdata.egg-info/top_level.txt
django_objectdumpdata/management/__init__.py
django_objectdumpdata/management/commands/__init__.py
django_objectdumpdata/management/commands/objectdumpdata.py