Metadata-Version: 1.1
Name: django-objectdumpdata
Version: 0.1.0
Summary: Creates django fixtures using a unique object and its related objects
Home-page: https://github.com/orige/django-objectdumpdata
Author: Eduardo Orige
Author-email: eduardo.orige@gmail.com
License: BSD
Keywords: django-objectdumpdata
Platform: UNKNOWN
Classifier: Development Status :: 3 - Alpha
Classifier: Framework :: Django
Classifier: Intended Audience :: Developers
Classifier: License :: OSI Approved :: BSD License
Classifier: Natural Language :: English
Classifier: Programming Language :: Python :: 2
Classifier: Programming Language :: Python :: 2.7
Classifier: Programming Language :: Python :: 3
Classifier: Programming Language :: Python :: 3.3
Classifier: Programming Language :: Python :: 3.4
